cancel_contexts/__init__.py
cancel_contexts/contexts/__init__.py
cancel_contexts/contexts/base.py
cancel_contexts/contexts/cancel.py
cancel_contexts/contexts/protocols.py
cancel_contexts/contexts/timeout.py
cancel_contexts/exceptions.py
cancel_contexts-0.1.3.dist-info/LICENSE
cancel_contexts-0.1.3.dist-info/METADATA
cancel_contexts-0.1.3.dist-info/WHEEL
cancel_contexts-0.1.3.dist-info/RECORD
