Metadata-Version: 2.1
Name: cancel-contexts
Version: 0.1.3
Summary: Realisation for canceling contexts (cancelled tokens) for Python
Home-page: https://github.com/alpden550/cancel-contexts
License: MIT
Keywords: python,python3,cancel token,cancel context
Author: Denis Novikov
Author-email: alpden550@gmail.com
Requires-Python: >=3.11,<4.0
Classifier: Development Status :: 4 - Beta
Classifier: Intended Audience :: Developers
Classifier: Intended Audience :: Education
Classifier: Intended Audience :: Information Technology
Classifier: Intended Audience :: Science/Research
Classifier: Intended Audience :: System Administrators
Classifier: License :: OSI Approved :: MIT License
Classifier: Operating System :: OS Independent
Classifier: Programming Language :: Python :: 3
Classifier: Programming Language :: Python :: 3.11
Classifier: Programming Language :: Python :: 3.12
Classifier: Programming Language :: Python :: 3 :: Only
Classifier: Topic :: Software Development :: Libraries :: Python Modules
Classifier: Topic :: Utilities
Classifier: Typing :: Typed
Requires-Dist: ruff (>=0.4.3,<0.5.0)
Project-URL: Repository, https://github.com/alpden550/cancel-contexts
